{
  "placeholderImages": [
    {
      "id": "mindful-breathing",
      "description": "A 5-minute guided breathing exercise to calm your mind.",
      "imageUrl": "https://picsum.photos/seed/101/600/400",
      "imageHint": "serene nature"
    },
    {
      "id": "body-scan",
      "description": "A 10-minute body scan meditation to release tension.",
      "imageUrl": "https://picsum.photos/seed/102/600/400",
      "imageHint": "calm water"
    },
    {
      "id": "nature-sounds",
      "description": "Listen to the soothing sounds of nature for 15 minutes.",
      "imageUrl": "https://picsum.photos/seed/103/600/400",
      "imageHint": "forest path"
    }
  ]
}
